cblaster/__init__.py
cblaster/classes.py
cblaster/config.py
cblaster/context.py
cblaster/database.py
cblaster/extract.py
cblaster/extract_clusters.py
cblaster/formatters.py
cblaster/genome_parsers.py
cblaster/helpers.py
cblaster/hmm_search.py
cblaster/intermediate_genes.py
cblaster/local.py
cblaster/main.py
cblaster/parsers.py
cblaster/plot.py
cblaster/plot_clusters.py
cblaster/remote.py
cblaster/sql.py
cblaster/gui/__init__.py
cblaster/gui/citation.py
cblaster/gui/config.py
cblaster/gui/extract.py
cblaster/gui/extract_clusters.py
cblaster/gui/gne.py
cblaster/gui/main.py
cblaster/gui/makedb.py
cblaster/gui/parts.py
cblaster/gui/plot_clusters.py
cblaster/gui/search.py
cblaster/plot/cblaster.html
cblaster/plot/cblaster.js
cblaster/plot/d3.min.js
cblaster/plot/gne.html
cblaster/plot/gne.js
cblaster/plot/index.css
tests/__init__.py
tests/test_classes.py
tests/test_context.py
tests/test_database.py
tests/test_genome_parsers.py
tests/test_helpers.py
tests/test_local.py
tests/test_main.py
tests/test_parsers.py
tests/test_remote.py
cblaster-1.3.20.dist-info/LICENSE
cblaster-1.3.20.dist-info/METADATA
cblaster-1.3.20.dist-info/WHEEL
cblaster-1.3.20.dist-info/entry_points.txt
cblaster-1.3.20.dist-info/top_level.txt
cblaster-1.3.20.dist-info/RECORD
