Metadata-Version: 2.1
Name: cblaster
Version: 1.3.20
Home-page: https://github.com/gamcil/cblaster
Author: Cameron Gilchrist
License: MIT
Classifier: Programming Language :: Python :: 3
Classifier: License :: OSI Approved :: MIT License
Classifier: Operating System :: OS Independent
Classifier: Intended Audience :: Science/Research
Classifier: Topic :: Scientific/Engineering :: Bio-Informatics
Classifier: License :: OSI Approved :: MIT License
Requires-Python: >=3.6
License-File: LICENSE
Requires-Dist: biopython
Requires-Dist: requests
Requires-Dist: numpy
Requires-Dist: scipy
Requires-Dist: PySimpleGUI
Requires-Dist: Biopython
Requires-Dist: clinker>=0.0.15
Requires-Dist: gffutils
Requires-Dist: appdirs
Requires-Dist: genomicsqlite; platform_machine != "arm64"
Requires-Dist: defusedxml
